Metadata-Version: 1.0
Name: jumgrafdash
Version: 1.0
Summary: Json formatter only for Jumbotail
Home-page: http://github.com/gauravmhkd25/Jumbotail
Author: Gaurav Mahakud
Author-email: gaurav.mahakud@jumbotail.com
License: JUMBOTAIL
Platform: UNKNOWN
